payload_crc.v
/*
This Module implements the parsing Moore FSM of Payload and CRC Fields.
Since no validation is required, parsing of Payload and CRC problem 
reduces to a counter that counts 50 bytes.
*/
module payload_crc(
		input clock,
		input reset,
		input enable,
		output packet_size_valid,
		output [3:0] valid_packet_counter
	);

//Inputs: all ACTIVE HIGH
wire clock, enable, reset;

//Output: all ACTIVE HIGH
reg packet_size_valid;
reg [3:0] valid_packet_counter;

//Counter
reg [5:0] bytes_counter;

always @(enable) begin
	if(enable == 1'b0)begin
		bytes_counter <= 1;
		packet_size_valid <= 1'b0;
	end
end

always @(posedge clock) begin
	if(reset == 1'b1) begin //synchronus active high reset
		bytes_counter <= 1'b0;
		packet_size_valid <= 1'b0;
		valid_packet_counter <= 4'b0;
	end
	// if (enable == 1'b0) begin
	// 	bytes_counter <= 1;
	// 	packet_size_valid <= 1'b0;
	// end 
	else begin
		bytes_counter = bytes_counter + 1; 
		if (bytes_counter == 50) begin
			packet_size_valid <= 1'b1;
			valid_packet_counter <= valid_packet_counter + 1; 
		end
	end
end

endmodule

header_fsm.v
/*
This Module implements the parsing Moore FSM of Ethernet Header Fields 
*/
module header_fsm(
		input clock,
		input reset,
		input enable,
		input [7:0] data,
		output preamble_valid,
		output dst_addr_valid,
		output src_addr_valid,
		output type_length_valid
	);

//Inputs: all ACTIVE HIGH
wire [7:0] data;
wire clock, enable;

//Outputs: all ACTIVE HIGH
reg preamble_valid, dst_addr_valid
	, src_addr_valid, type_length_valid;

parameter [4:0] STATE0  = 5'b00000;
parameter [4:0] STATE1  = 5'b00001;
parameter [4:0] STATE2  = 5'b00010;
parameter [4:0] STATE3  = 5'b00011;
parameter [4:0] STATE4  = 5'b00100;
parameter [4:0] STATE5  = 5'b00101;
parameter [4:0] STATE6  = 5'b00110;
parameter [4:0] STATE7  = 5'b00111;
parameter [4:0] STATE8  = 5'b01000;
parameter [4:0] STATE9  = 5'b01001;
parameter [4:0] STATE10 = 5'b01010;
parameter [4:0] STATE11 = 5'b01011;
parameter [4:0] STATE12 = 5'b01100;
parameter [4:0] STATE13 = 5'b01101;
parameter [4:0] STATE14 = 5'b01110;
parameter [4:0] STATE15 = 5'b01111;
parameter [4:0] STATE16 = 5'b10000;
parameter [4:0] STATE17 = 5'b10001;
parameter [4:0] STATE18 = 5'b10010;
parameter [4:0] STATE19 = 5'b10011;
parameter [4:0] STATE20 = 5'b10100;
parameter [4:0] STATE21 = 5'b10101;
parameter [4:0] STATE22 = 5'b10110;

//23 states
reg [4:0] state = STATE0;
reg [4:0] next_state = STATE0;


//COMBINATIONAL LOGIC
always @(state or data or enable) begin
	next_state = 0; //prevent latches
	if (enable == 1'b1) begin
		case({state,data}) 
			{STATE0,8'h55}:next_state = STATE1;//1st byte PREAMBLE
			{STATE1,8'h55}:next_state = STATE2;//2nd byte PREAMBLE
			{STATE2,8'h55}:next_state = STATE3;//3rd byte PREAMBLE
			{STATE3,8'h55}:next_state = STATE4;//4th byte PREAMBLE
			{STATE4,8'h55}:next_state = STATE5;//5th byte PREAMBLE
			{STATE5,8'h55}:next_state = STATE6;//6th byte PREAMBLE
			{STATE6,8'h55}:next_state = STATE7;//7th byte PREAMBLE
			{STATE7,8'hD5}:next_state = STATE8;//8th byte PREAMBLE			
			
			{STATE8,8'h01}:next_state = STATE9;//1st byte DST_ADDRESS
			{STATE9,8'h02}:next_state = STATE10;//2nd byte DST_ADDRESS
			{STATE10,8'h03}:next_state = STATE11;//3rd byte DST_ADDRESS
			{STATE11,8'h04}:next_state = STATE12;//4th byte DST_ADDRESS
			{STATE12,8'h05}:next_state = STATE13;//5th byte DST_ADDRESS
			{STATE13,8'h06}:next_state = STATE14;//6th byte DST_ADDRESS

			{STATE14,8'hFF}:next_state = STATE15;//1st byte SRC_ADDRESS
			{STATE15,8'hFE}:next_state = STATE16;//2nd byte SRC_ADDRESS
			{STATE16,8'hFD}:next_state = STATE17;//3rd byte SRC_ADDRESS
			{STATE17,8'hFC}:next_state = STATE18;//4th byte SRC_ADDRESS
			{STATE18,8'hFB}:next_state = STATE19;//5th byte SRC_ADDRESS
			{STATE19,8'hFA}:next_state = STATE20;//6th byte SRC_ADDRESS

			{STATE20,8'h08}:next_state = STATE21;//1st byte TYPE_LENGTH
			{STATE21,8'h00}:next_state = STATE22;//2nd byte TYPE_LENGTH

			default: next_state = STATE0; //anything Else -> start from begininng 
		endcase
	end
end

//SEQUENTIAL LOGIC
always @(posedge clock) begin //positive transition of clock 	
	if(reset == 1'b1) begin //synchronus active high reset
		state <= STATE0;
		preamble_valid <= 1'b0;
		dst_addr_valid <= 1'b0;
		src_addr_valid <= 1'b0;
		type_length_valid <= 1'b0;
	end
	else begin
		state = next_state; //blocking assignment to reflect in output immediately
		case(state)
			//STATE0 is equivilant to start (either during instantiation or failure during parsing)
			STATE0:begin
					preamble_valid <= 1'b0;
					dst_addr_valid <= 1'b0;
					src_addr_valid <= 1'b0;
					type_length_valid <= 1'b0;		
				end

			//STATE8 is equivilant to valid PREAMBLE received
			STATE8: begin
					preamble_valid <= 1'b1;
				end
			//STATE9 is equivilant to valid PREAMBLE received last posedge of clock
			STATE9:begin
					preamble_valid <= 1'b0;
				end

			//STATE14 is equivilant to valid DST_ADDRESS received
			STATE14: begin
					dst_addr_valid <= 1'b1;
				end
			//STATE9 is equivilant to valid DST_ADDRESS received last posedge of clock
			STATE15:begin
					dst_addr_valid <= 1'b0;
				end
			//STATE20 is equivilant to valid SRC_ADDRESS received
			STATE20: begin
					src_addr_valid <= 1'b1;
				end
			//STATE9 is equivilant to valid SRC_ADDRESS received last posedge of clock
			STATE21:begin
					src_addr_valid <= 1'b0;
				end
			//STATE8 is equivilant to valid TYPE_LENGTH received
			STATE22: begin
					type_length_valid <= 1'b1;
				end
		endcase		
	end
end

endmodule

control_fsm.v
/*
This module cotains the Ethernet Packet Detector implementation
of Cobinational and Sequential parts of the controller Logic.
*/
module control_fsm(
		input clock,
		input reset,
		input control,
		input [7:0] data,
		input type_length_valid,
		input packet_size_valid,
		output enable_header,
		output enable_payload
	);

//Inputs: all ACTIVE HIGH
wire clock, reset, control, 
	type_length_valid, packet_size_valid;
wire [7:0] data;

//Outputs: all ACTIVE HIGH
wire enable_header, enable_payload; //enable signals for header and payload modules

//3 states
parameter [1:0] STATE0 = 2'b00;
parameter [1:0] STATE1 = 2'b01;
parameter [1:0] STATE2 = 2'b10;

reg [1:0] state = STATE0;
reg [1:0] next_state = STATE0;

assign enable_header = control && !state;
assign enable_payload = control & state;

// always @(*) begin
// 	enable_header <= control && !state;
// 	enable_payload <= control & state;
// end

always @(type_length_valid or packet_size_valid) begin
	next_state = STATE0; //prevent unintended latches
	case(state)
		STATE0:begin
			next_state = STATE0;
			if(type_length_valid == 1'b1 && control == 1'b1)begin
				next_state = STATE1;
			end
		end
		STATE1:begin
			next_state = STATE1;
			if(packet_size_valid == 1'b1)begin
				next_state = STATE2;
			end
			// if(control == 1'b0)begin
			// 	next_state = STATE0;
			// end
		end
		STATE2:begin
			next_state = STATE2;
			if(control == 1'b0 && data == 8'h00)begin
				next_state = STATE0;
			end
		end
	endcase
end

always @(posedge clock) begin
	// reset and control are synchronus active high
	// if (reset == 1'b1 || control == 1'b0) begin
	// 	state <= STATE0;
	// end
	if (reset == 1'b1) begin // reset is synchronus active high
		state <= STATE0;
		// enable_header = 1'b1;
		// enable_payload = 1'b0;
	end
	else begin
		state = next_state; //blocking assignment
	end
end

endmodule

epd.v
/*
This module cotains the Ethernet Packet Detector implementation
of Cobinational and Sequential parts of the controller Logic.
*/
`include "header_fsm.v"
`include "payload_crc.v"
`include "control_fsm.v"

module epd(
		input clock,
		input reset,
		input [7:0] data,
		input control,
		output preamble_valid,
		output dst_addr_valid,
		output src_addr_valid,
		output type_length_valid,
		output packet_size_valid,
		output [3:0] valid_packet_counter 
	);

//Inputs: all ACTIVE HIGH
wire clock, reset, control;
wire [7:0] data;

//Outputs: all ACTIVE HIGH
wire preamble_valid, src_addr_valid, 
	dst_addr_valid, type_length_valid,
	packet_size_valid;
wire [3:0] valid_packet_counter;

control_fsm U_control_fsm(
clock,
reset,
control,
type_length_valid,
packet_size_valid,
enable_header,
enable_payload
);

header_fsm U_header_fsm(
.clock (clock),
.reset (reset),
.enable (enable_header),
.data (data),
.preamble_valid (preamble_valid),
.dst_addr_valid (dst_addr_valid),
.src_addr_valid (src_addr_valid),
.type_length_valid (type_length_valid)
);

payload_crc U_payload_crc(
.clock (clock),
.reset (reset),
.enable (enable_payload),
.packet_size_valid (packet_size_valid),
.valid_packet_counter (valid_packet_counter)
);

endmodule

tests/multiple_packets_pld_cntrl.v
// Test sends multiple packets while control is set to low during
// sending of payload of a former packet. 
`include "epd.v"

module multiple_packets_pld_cntrl;

reg clock, reset, control;
reg [7:0] data;

wire preamble_valid, dst_addr_valid, src_addr_valid,
	type_length_valid, packet_size_valid;
wire [3:0] valid_packet_counter;

epd U_epd(
clock,
reset,
data,
control,
preamble_valid,
dst_addr_valid,
src_addr_valid,
type_length_valid,
packet_size_valid,
valid_packet_counter 
);


initial begin
	$dumpfile("multiple_packets_pld_cntrl.vcd");
	$dumpvars(0,multiple_packets_pld_cntrl);
	
	clock = 0;
	
	control = 1;
	data = 0;
	reset = 0;
	
	//***************************** First packet ******************************
	//valid preamble
	repeat (7) #2 data = 8'h55;
	#2 data = 8'hD5;

	//valid DST
	#2 data = 8'h01; #2 data = 8'h02; #2 data = 8'h03; #2 data = 8'h04;
    #2 data = 8'h05; #2 data = 8'h06;

    //valid SRC
    #2 data = 8'hFF; #2 data = 8'hFE; #2 data = 8'hFD; #2 data = 8'hFC;
    #2 data = 8'hFB; #2 data = 8'hFA;

	//valid type_length
	#2 data = 8'h08; #2 data = 8'h00;

	//send payload and crc
	repeat (49) #2 data = 8'h55;#2 data = 8'hFF;

	//send one IFG
	#2 control = 0;
    data = 8'h00;
    #2 control = 1;

    //***************************** Second packet ******************************
	//valid preamble
	repeat (7) #2 data = 8'h55;
	#2 data = 8'hD5;

	//valid DST
	#2 data = 8'h01; #2 data = 8'h02; #2 data = 8'h03; #2 data = 8'h04;
    #2 data = 8'h05; #2 data = 8'h06;

    //valid SRC
    #2 data = 8'hFF; #2 data = 8'hFE; #2 data = 8'hFD; #2 data = 8'hFC;
    #2 data = 8'hFB; #2 data = 8'hFA;
    
	//valid type_length
	#2 data = 8'h08; #2 data = 8'h00;

	//send payload and crc
	repeat (29) #2 data = 8'h55;
	#2 control = 0; // CONTROL SET TO LOW DURING SECOND PACKET
	repeat (20) #2 data = 8'h55;
	#2 data = 8'h56;

	//send multiple IFGs
	#2 control = 0;
    data = 8'h00;
    #6 control = 1;

    //***************************** Third packet ******************************
	//valid preamble
	repeat (7) #2 data = 8'h55;
	#2 data = 8'hD5;

	//valid DST
	#2 data = 8'h01; #2 data = 8'h02; #2 data = 8'h03; #2 data = 8'h04;
    #2 data = 8'h05; #2 data = 8'h06;

    //valid SRC
    #2 data = 8'hFF; #2 data = 8'hFE; #2 data = 8'hFD; #2 data = 8'hFC;
    #2 data = 8'hFB; #2 data = 8'hFA;

	//valid type_length
	#2 data = 8'h08; #2 data = 8'h00;

	//send payload and crc
	repeat (49) #2 data = 8'h55;#2 data = 8'h56;

	//send one IFG
	#2 control = 0;
    data = 8'h00;
    #2 control = 1;

    #10 $finish;
end


//clock generator
always
	#1 clock =~ clock;

endmodule

tests/multiple_packets_pld_cntrl.vcd
$date
	Wed Mar  1 07:48:57 2017
$end
$version
	Icarus Verilog
$end
$timescale
	1s
$end
$scope module multiple_packets_pld_cntrl $end
$var wire 1 ! dst_addr_valid $end
$var wire 1 " packet_size_valid $end
$var wire 1 # preamble_valid $end
$var wire 1 $ src_addr_valid $end
$var wire 1 % type_length_valid $end
$var wire 4 & valid_packet_counter [3:0] $end
$var reg 1 ' clock $end
$var reg 1 ( control $end
$var reg 8 ) data [7:0] $end
$var reg 1 * reset $end
$scope module U_epd $end
$var wire 1 + clock $end
$var wire 1 , control $end
$var wire 8 - data [7:0] $end
$var wire 1 ! dst_addr_valid $end
$var wire 1 . enable_header $end
$var wire 1 / enable_payload $end
$var wire 1 " packet_size_valid $end
$var wire 1 # preamble_valid $end
$var wire 1 0 reset $end
$var wire 1 $ src_addr_valid $end
$var wire 1 % type_length_valid $end
$var wire 4 1 valid_packet_counter [3:0] $end
$scope module U_control_fsm $end
$var wire 1 + clock $end
$var wire 1 , control $end
$var wire 8 2 data [7:0] $end
$var wire 1 . enable_header $end
$var wire 1 / enable_payload $end
$var wire 1 " packet_size_valid $end
$var wire 1 0 reset $end
$var wire 1 % type_length_valid $end
$var reg 2 3 next_state [1:0] $end
$var reg 2 4 state [1:0] $end
$upscope $end
$scope module U_header_fsm $end
$var wire 1 + clock $end
$var wire 8 5 data [7:0] $end
$var wire 1 . enable $end
$var wire 1 0 reset $end
$var reg 1 6 dst_addr_valid $end
$var reg 5 7 next_state [4:0] $end
$var reg 1 8 preamble_valid $end
$var reg 1 9 src_addr_valid $end
$var reg 5 : state [4:0] $end
$var reg 1 ; type_length_valid $end
$upscope $end
$scope module U_payload_crc $end
$var wire 1 + clock $end
$var wire 1 / enable $end
$var wire 1 0 reset $end
$var reg 6 < bytes_counter [5:0] $end
$var reg 1 = packet_size_valid $end
$var reg 4 > valid_packet_counter [3:0] $end
$upscope $end
$upscope $end
$upscope $end
$enddefinitions $end
#0
$dumpvars
b0 >
x=
bx <
x;
b0 :
x9
x8
b0 7
x6
b0 5
b0 4
b0 3
b0 2
b0 1
00
0/
1.
b0 -
1,
0+
0*
b0 )
1(
0'
b0 &
x%
x$
x#
x"
x!
$end
#1
0;
0%
09
0$
06
0!
08
0#
0=
0"
b1 <
1'
1+
#2
b1 7
0'
0+
b1010101 )
b1010101 -
b1010101 2
b1010101 5
#3
b10 7
b1 :
1'
1+
#4
0'
0+
#5
b11 7
b10 :
1'
1+
#6
0'
0+
#7
b100 7
b11 :
1'
1+
#8
0'
0+
#9
b101 7
b100 :
1'
1+
#10
0'
0+
#11
b110 7
b101 :
1'
1+
#12
0'
0+
#13
b111 7
b110 :
1'
1+
#14
0'
0+
#15
b0 7
b111 :
1'
1+
#16
b1000 7
0'
0+
b11010101 )
b11010101 -
b11010101 2
b11010101 5
#17
18
1#
b0 7
b1000 :
1'
1+
#18
b1001 7
0'
0+
b1 )
b1 -
b1 2
b1 5
#19
08
0#
b0 7
b1001 :
1'
1+
#20
b1010 7
0'
0+
b10 )
b10 -
b10 2
b10 5
#21
b0 7
b1010 :
1'
1+
#22
b1011 7
0'
0+
b11 )
b11 -
b11 2
b11 5
#23
b0 7
b1011 :
1'
1+
#24
b1100 7
0'
0+
b100 )
b100 -
b100 2
b100 5
#25
b0 7
b1100 :
1'
1+
#26
b1101 7
0'
0+
b101 )
b101 -
b101 2
b101 5
#27
b0 7
b1101 :
1'
1+
#28
b1110 7
0'
0+
b110 )
b110 -
b110 2
b110 5
#29
16
1!
b0 7
b1110 :
1'
1+
#30
b1111 7
0'
0+
b11111111 )
b11111111 -
b11111111 2
b11111111 5
#31
06
0!
b0 7
b1111 :
1'
1+
#32
b10000 7
0'
0+
b11111110 )
b11111110 -
b11111110 2
b11111110 5
#33
b0 7
b10000 :
1'
1+
#34
b10001 7
0'
0+
b11111101 )
b11111101 -
b11111101 2
b11111101 5
#35
b0 7
b10001 :
1'
1+
#36
b10010 7
0'
0+
b11111100 )
b11111100 -
b11111100 2
b11111100 5
#37
b0 7
b10010 :
1'
1+
#38
b10011 7
0'
0+
b11111011 )
b11111011 -
b11111011 2
b11111011 5
#39
b0 7
b10011 :
1'
1+
#40
b10100 7
0'
0+
b11111010 )
b11111010 -
b11111010 2
b11111010 5
#41
19
1$
b0 7
b10100 :
1'
1+
#42
b10101 7
0'
0+
b1000 )
b1000 -
b1000 2
b1000 5
#43
09
0$
b0 7
b10101 :
1'
1+
#44
b10110 7
0'
0+
b0 )
b0 -
b0 2
b0 5
#45
b1 3
1;
1%
b0 7
b10110 :
1'
1+
#46
0'
0+
b1010101 )
b1010101 -
b1010101 2
b1010101 5
#47
0;
0%
1/
b1 3
0.
b0 :
b1 4
1'
1+
#48
0'
0+
#49
b10 <
1'
1+
#50
0'
0+
#51
b11 <
1'
1+
#52
0'
0+
#53
b100 <
1'
1+
#54
0'
0+
#55
b101 <
1'
1+
#56
0'
0+
#57
b110 <
1'
1+
#58
0'
0+
#59
b111 <
1'
1+
#60
0'
0+
#61
b1000 <
1'
1+
#62
0'
0+
#63
b1001 <
1'
1+
#64
0'
0+
#65
b1010 <
1'
1+
#66
0'
0+
#67
b1011 <
1'
1+
#68
0'
0+
#69
b1100 <
1'
1+
#70
0'
0+
#71
b1101 <
1'
1+
#72
0'
0+
#73
b1110 <
1'
1+
#74
0'
0+
#75
b1111 <
1'
1+
#76
0'
0+
#77
b10000 <
1'
1+
#78
0'
0+
#79
b10001 <
1'
1+
#80
0'
0+
#81
b10010 <
1'
1+
#82
0'
0+
#83
b10011 <
1'
1+
#84
0'
0+
#85
b10100 <
1'
1+
#86
0'
0+
#87
b10101 <
1'
1+
#88
0'
0+
#89
b10110 <
1'
1+
#90
0'
0+
#91
b10111 <
1'
1+
#92
0'
0+
#93
b11000 <
1'
1+
#94
0'
0+
#95
b11001 <
1'
1+
#96
0'
0+
#97
b11010 <
1'
1+
#98
0'
0+
#99
b11011 <
1'
1+
#100
0'
0+
#101
b11100 <
1'
1+
#102
0'
0+
#103
b11101 <
1'
1+
#104
0'
0+
#105
b11110 <
1'
1+
#106
0'
0+
#107
b11111 <
1'
1+
#108
0'
0+
#109
b100000 <
1'
1+
#110
0'
0+
#111
b100001 <
1'
1+
#112
0'
0+
#113
b100010 <
1'
1+
#114
0'
0+
#115
b100011 <
1'
1+
#116
0'
0+
#117
b100100 <
1'
1+
#118
0'
0+
#119
b100101 <
1'
1+
#120
0'
0+
#121
b100110 <
1'
1+
#122
0'
0+
#123
b100111 <
1'
1+
#124
0'
0+
#125
b101000 <
1'
1+
#126
0'
0+
#127
b101001 <
1'
1+
#128
0'
0+
#129
b101010 <
1'
1+
#130
0'
0+
#131
b101011 <
1'
1+
#132
0'
0+
#133
b101100 <
1'
1+
#134
0'
0+
#135
b101101 <
1'
1+
#136
0'
0+
#137
b101110 <
1'
1+
#138
0'
0+
#139
b101111 <
1'
1+
#140
0'
0+
#141
b110000 <
1'
1+
#142
0'
0+
#143
b110001 <
1'
1+
#144
0'
0+
b11111111 )
b11111111 -
b11111111 2
b11111111 5
#145
b10 3
b1 >
b1 &
b1 1
1=
1"
b110010 <
1'
1+
#146
0/
0'
0+
b0 )
b0 -
b0 2
b0 5
0(
0,
#147
b1 <
0=
0"
b0 3
b0 4
1'
1+
#148
1.
0'
0+
1(
1,
#149
1'
1+
#150
b1 7
0'
0+
b1010101 )
b1010101 -
b1010101 2
b1010101 5
#151
b10 7
b1 :
1'
1+
#152
0'
0+
#153
b11 7
b10 :
1'
1+
#154
0'
0+
#155
b100 7
b11 :
1'
1+
#156
0'
0+
#157
b101 7
b100 :
1'
1+
#158
0'
0+
#159
b110 7
b101 :
1'
1+
#160
0'
0+
#161
b111 7
b110 :
1'
1+
#162
0'
0+
#163
b0 7
b111 :
1'
1+
#164
b1000 7
0'
0+
b11010101 )
b11010101 -
b11010101 2
b11010101 5
#165
18
1#
b0 7
b1000 :
1'
1+
#166
b1001 7
0'
0+
b1 )
b1 -
b1 2
b1 5
#167
08
0#
b0 7
b1001 :
1'
1+
#168
b1010 7
0'
0+
b10 )
b10 -
b10 2
b10 5
#169
b0 7
b1010 :
1'
1+
#170
b1011 7
0'
0+
b11 )
b11 -
b11 2
b11 5
#171
b0 7
b1011 :
1'
1+
#172
b1100 7
0'
0+
b100 )
b100 -
b100 2
b100 5
#173
b0 7
b1100 :
1'
1+
#174
b1101 7
0'
0+
b101 )
b101 -
b101 2
b101 5
#175
b0 7
b1101 :
1'
1+
#176
b1110 7
0'
0+
b110 )
b110 -
b110 2
b110 5
#177
16
1!
b0 7
b1110 :
1'
1+
#178
b1111 7
0'
0+
b11111111 )
b11111111 -
b11111111 2
b11111111 5
#179
06
0!
b0 7
b1111 :
1'
1+
#180
b10000 7
0'
0+
b11111110 )
b11111110 -
b11111110 2
b11111110 5
#181
b0 7
b10000 :
1'
1+
#182
b10001 7
0'
0+
b11111101 )
b11111101 -
b11111101 2
b11111101 5
#183
b0 7
b10001 :
1'
1+
#184
b10010 7
0'
0+
b11111100 )
b11111100 -
b11111100 2
b11111100 5
#185
b0 7
b10010 :
1'
1+
#186
b10011 7
0'
0+
b11111011 )
b11111011 -
b11111011 2
b11111011 5
#187
b0 7
b10011 :
1'
1+
#188
b10100 7
0'
0+
b11111010 )
b11111010 -
b11111010 2
b11111010 5
#189
19
1$
b0 7
b10100 :
1'
1+
#190
b10101 7
0'
0+
b1000 )
b1000 -
b1000 2
b1000 5
#191
09
0$
b0 7
b10101 :
1'
1+
#192
b10110 7
0'
0+
b0 )
b0 -
b0 2
b0 5
#193
b1 3
1;
1%
b0 7
b10110 :
1'
1+
#194
0'
0+
b1010101 )
b1010101 -
b1010101 2
b1010101 5
#195
0;
0%
1/
b1 3
0.
b0 :
b1 4
1'
1+
#196
0'
0+
#197
b10 <
1'
1+
#198
0'
0+
#199
b11 <
1'
1+
#200
0'
0+
#201
b100 <
1'
1+
#202
0'
0+
#203
b101 <
1'
1+
#204
0'
0+
#205
b110 <
1'
1+
#206
0'
0+
#207
b111 <
1'
1+
#208
0'
0+
#209
b1000 <
1'
1+
#210
0'
0+
#211
b1001 <
1'
1+
#212
0'
0+
#213
b1010 <
1'
1+
#214
0'
0+
#215
b1011 <
1'
1+
#216
0'
0+
#217
b1100 <
1'
1+
#218
0'
0+
#219
b1101 <
1'
1+
#220
0'
0+
#221
b1110 <
1'
1+
#222
0'
0+
#223
b1111 <
1'
1+
#224
0'
0+
#225
b10000 <
1'
1+
#226
0'
0+
#227
b10001 <
1'
1+
#228
0'
0+
#229
b10010 <
1'
1+
#230
0'
0+
#231
b10011 <
1'
1+
#232
0'
0+
#233
b10100 <
1'
1+
#234
0'
0+
#235
b10101 <
1'
1+
#236
0'
0+
#237
b10110 <
1'
1+
#238
0'
0+
#239
b10111 <
1'
1+
#240
0'
0+
#241
b11000 <
1'
1+
#242
0'
0+
#243
b11001 <
1'
1+
#244
0'
0+
#245
b11010 <
1'
1+
#246
0'
0+
#247
b11011 <
1'
1+
#248
0'
0+
#249
b11100 <
1'
1+
#250
0'
0+
#251
b11101 <
1'
1+
#252
0/
0'
0+
0(
0,
#253
b0 3
b0 4
b1 <
1'
1+
#254
0'
0+
#255
1'
1+
#256
0'
0+
#257
1'
1+
#258
0'
0+
#259
1'
1+
#260
0'
0+
#261
1'
1+
#262
0'
0+
#263
1'
1+
#264
0'
0+
#265
1'
1+
#266
0'
0+
#267
1'
1+
#268
0'
0+
#269
1'
1+
#270
0'
0+
#271
1'
1+
#272
0'
0+
#273
1'
1+
#274
0'
0+
#275
1'
1+
#276
0'
0+
#277
1'
1+
#278
0'
0+
#279
1'
1+
#280
0'
0+
#281
1'
1+
#282
0'
0+
#283
1'
1+
#284
0'
0+
#285
1'
1+
#286
0'
0+
#287
1'
1+
#288
0'
0+
#289
1'
1+
#290
0'
0+
#291
1'
1+
#292
0'
0+
#293
1'
1+
#294
0'
0+
b1010110 )
b1010110 -
b1010110 2
b1010110 5
#295
1'
1+
#296
0'
0+
b0 )
b0 -
b0 2
b0 5
#297
1'
1+
#298
0'
0+
#299
1'
1+
#300
0'
0+
#301
1'
1+
#302
1.
0'
0+
1(
1,
#303
1'
1+
#304
b1 7
0'
0+
b1010101 )
b1010101 -
b1010101 2
b1010101 5
#305
b10 7
b1 :
1'
1+
#306
0'
0+
#307
b11 7
b10 :
1'
1+
#308
0'
0+
#309
b100 7
b11 :
1'
1+
#310
0'
0+
#311
b101 7
b100 :
1'
1+
#312
0'
0+
#313
b110 7
b101 :
1'
1+
#314
0'
0+
#315
b111 7
b110 :
1'
1+
#316
0'
0+
#317
b0 7
b111 :
1'
1+
#318
b1000 7
0'
0+
b11010101 )
b11010101 -
b11010101 2
b11010101 5
#319
18
1#
b0 7
b1000 :
1'
1+
#320
b1001 7
0'
0+
b1 )
b1 -
b1 2
b1 5
#321
08
0#
b0 7
b1001 :
1'
1+
#322
b1010 7
0'
0+
b10 )
b10 -
b10 2
b10 5
#323
b0 7
b1010 :
1'
1+
#324
b1011 7
0'
0+
b11 )
b11 -
b11 2
b11 5
#325
b0 7
b1011 :
1'
1+
#326
b1100 7
0'
0+
b100 )
b100 -
b100 2
b100 5
#327
b0 7
b1100 :
1'
1+
#328
b1101 7
0'
0+
b101 )
b101 -
b101 2
b101 5
#329
b0 7
b1101 :
1'
1+
#330
b1110 7
0'
0+
b110 )
b110 -
b110 2
b110 5
#331
16
1!
b0 7
b1110 :
1'
1+
#332
b1111 7
0'
0+
b11111111 )
b11111111 -
b11111111 2
b11111111 5
#333
06
0!
b0 7
b1111 :
1'
1+
#334
b10000 7
0'
0+
b11111110 )
b11111110 -
b11111110 2
b11111110 5
#335
b0 7
b10000 :
1'
1+
#336
b10001 7
0'
0+
b11111101 )
b11111101 -
b11111101 2
b11111101 5
#337
b0 7
b10001 :
1'
1+
#338
b10010 7
0'
0+
b11111100 )
b11111100 -
b11111100 2
b11111100 5
#339
b0 7
b10010 :
1'
1+
#340
b10011 7
0'
0+
b11111011 )
b11111011 -
b11111011 2
b11111011 5
#341
b0 7
b10011 :
1'
1+
#342
b10100 7
0'
0+
b11111010 )
b11111010 -
b11111010 2
b11111010 5
#343
19
1$
b0 7
b10100 :
1'
1+
#344
b10101 7
0'
0+
b1000 )
b1000 -
b1000 2
b1000 5
#345
09
0$
b0 7
b10101 :
1'
1+
#346
b10110 7
0'
0+
b0 )
b0 -
b0 2
b0 5
#347
b1 3
1;
1%
b0 7
b10110 :
1'
1+
#348
0'
0+
b1010101 )
b1010101 -
b1010101 2
b1010101 5
#349
0;
0%
1/
b1 3
0.
b0 7
b1 4
b0 :
1'
1+
#350
0'
0+
#351
b10 <
1'
1+
#352
0'
0+
#353
b11 <
1'
1+
#354
0'
0+
#355
b100 <
1'
1+
#356
0'
0+
#357
b101 <
1'
1+
#358
0'
0+
#359
b110 <
1'
1+
#360
0'
0+
#361
b111 <
1'
1+
#362
0'
0+
#363
b1000 <
1'
1+
#364
0'
0+
#365
b1001 <
1'
1+
#366
0'
0+
#367
b1010 <
1'
1+
#368
0'
0+
#369
b1011 <
1'
1+
#370
0'
0+
#371
b1100 <
1'
1+
#372
0'
0+
#373
b1101 <
1'
1+
#374
0'
0+
#375
b1110 <
1'
1+
#376
0'
0+
#377
b1111 <
1'
1+
#378
0'
0+
#379
b10000 <
1'
1+
#380
0'
0+
#381
b10001 <
1'
1+
#382
0'
0+
#383
b10010 <
1'
1+
#384
0'
0+
#385
b10011 <
1'
1+
#386
0'
0+
#387
b10100 <
1'
1+
#388
0'
0+
#389
b10101 <
1'
1+
#390
0'
0+
#391
b10110 <
1'
1+
#392
0'
0+
#393
b10111 <
1'
1+
#394
0'
0+
#395
b11000 <
1'
1+
#396
0'
0+
#397
b11001 <
1'
1+
#398
0'
0+
#399
b11010 <
1'
1+
#400
0'
0+
#401
b11011 <
1'
1+
#402
0'
0+
#403
b11100 <
1'
1+
#404
0'
0+
#405
b11101 <
1'
1+
#406
0'
0+
#407
b11110 <
1'
1+
#408
0'
0+
#409
b11111 <
1'
1+
#410
0'
0+
#411
b100000 <
1'
1+
#412
0'
0+
#413
b100001 <
1'
1+
#414
0'
0+
#415
b100010 <
1'
1+
#416
0'
0+
#417
b100011 <
1'
1+
#418
0'
0+
#419
b100100 <
1'
1+
#420
0'
0+
#421
b100101 <
1'
1+
#422
0'
0+
#423
b100110 <
1'
1+
#424
0'
0+
#425
b100111 <
1'
1+
#426
0'
0+
#427
b101000 <
1'
1+
#428
0'
0+
#429
b101001 <
1'
1+
#430
0'
0+
#431
b101010 <
1'
1+
#432
0'
0+
#433
b101011 <
1'
1+
#434
0'
0+
#435
b101100 <
1'
1+
#436
0'
0+
#437
b101101 <
1'
1+
#438
0'
0+
#439
b101110 <
1'
1+
#440
0'
0+
#441
b101111 <
1'
1+
#442
0'
0+
#443
b110000 <
1'
1+
#444
0'
0+
#445
b110001 <
1'
1+
#446
0'
0+
b1010110 )
b1010110 -
b1010110 2
b1010110 5
#447
b10 3
b10 >
b10 &
b10 1
1=
1"
b110010 <
1'
1+
#448
0/
0'
0+
b0 )
b0 -
b0 2
b0 5
0(
0,
#449
b1 <
0=
0"
b0 3
b0 4
1'
1+
#450
1.
0'
0+
1(
1,
