payload_crc.v
/*
This Module implements the parsing Moore FSM of Payload and CRC Fields.
Since no validation is required, parsing of Payload and CRC problem 
reduces to a counter that counts 50 bytes.
*/
module payload_crc(
		input clock,
		input reset,
		input enable,
		output packet_size_valid,
		output [3:0] valid_packet_counter
	);

//Inputs: all ACTIVE HIGH
wire clock, enable, reset;

//Output: all ACTIVE HIGH
reg packet_size_valid;
reg [3:0] valid_packet_counter;

//Counter
reg [5:0] bytes_counter;

always @(enable) begin
	if(enable == 1'b0)begin
		bytes_counter <= 1;
		packet_size_valid <= 1'b0;
	end
end

always @(posedge clock) begin
	if(reset == 1'b1) begin //synchronus active high reset
		bytes_counter <= 1'b0;
		packet_size_valid <= 1'b0;
		valid_packet_counter <= 4'b0;
	end
	// if (enable == 1'b0) begin
	// 	bytes_counter <= 1;
	// 	packet_size_valid <= 1'b0;
	// end 
	else begin
		bytes_counter = bytes_counter + 1; 
		if (bytes_counter == 50) begin
			packet_size_valid <= 1'b1;
			valid_packet_counter <= valid_packet_counter + 1; 
		end
	end
end

endmodule

header_fsm.v
/*
This Module implements the parsing Moore FSM of Ethernet Header Fields 
*/
module header_fsm(
		input clock,
		input reset,
		input enable,
		input [7:0] data,
		output preamble_valid,
		output dst_addr_valid,
		output src_addr_valid,
		output type_length_valid
	);

//Inputs: all ACTIVE HIGH
wire [7:0] data;
wire clock, enable;

//Outputs: all ACTIVE HIGH
reg preamble_valid, dst_addr_valid
	, src_addr_valid, type_length_valid;

parameter [4:0] STATE0  = 5'b00000;
parameter [4:0] STATE1  = 5'b00001;
parameter [4:0] STATE2  = 5'b00010;
parameter [4:0] STATE3  = 5'b00011;
parameter [4:0] STATE4  = 5'b00100;
parameter [4:0] STATE5  = 5'b00101;
parameter [4:0] STATE6  = 5'b00110;
parameter [4:0] STATE7  = 5'b00111;
parameter [4:0] STATE8  = 5'b01000;
parameter [4:0] STATE9  = 5'b01001;
parameter [4:0] STATE10 = 5'b01010;
parameter [4:0] STATE11 = 5'b01011;
parameter [4:0] STATE12 = 5'b01100;
parameter [4:0] STATE13 = 5'b01101;
parameter [4:0] STATE14 = 5'b01110;
parameter [4:0] STATE15 = 5'b01111;
parameter [4:0] STATE16 = 5'b10000;
parameter [4:0] STATE17 = 5'b10001;
parameter [4:0] STATE18 = 5'b10010;
parameter [4:0] STATE19 = 5'b10011;
parameter [4:0] STATE20 = 5'b10100;
parameter [4:0] STATE21 = 5'b10101;
parameter [4:0] STATE22 = 5'b10110;

//23 states
reg [4:0] state = STATE0;
reg [4:0] next_state = STATE0;


//COMBINATIONAL LOGIC
always @(state or data or enable) begin
	next_state = 0; //prevent latches
	if (enable == 1'b1) begin
		case({state,data}) 
			{STATE0,8'h55}:next_state = STATE1;//1st byte PREAMBLE
			{STATE1,8'h55}:next_state = STATE2;//2nd byte PREAMBLE
			{STATE2,8'h55}:next_state = STATE3;//3rd byte PREAMBLE
			{STATE3,8'h55}:next_state = STATE4;//4th byte PREAMBLE
			{STATE4,8'h55}:next_state = STATE5;//5th byte PREAMBLE
			{STATE5,8'h55}:next_state = STATE6;//6th byte PREAMBLE
			{STATE6,8'h55}:next_state = STATE7;//7th byte PREAMBLE
			{STATE7,8'hD5}:next_state = STATE8;//8th byte PREAMBLE			
			
			{STATE8,8'h01}:next_state = STATE9;//1st byte DST_ADDRESS
			{STATE9,8'h02}:next_state = STATE10;//2nd byte DST_ADDRESS
			{STATE10,8'h03}:next_state = STATE11;//3rd byte DST_ADDRESS
			{STATE11,8'h04}:next_state = STATE12;//4th byte DST_ADDRESS
			{STATE12,8'h05}:next_state = STATE13;//5th byte DST_ADDRESS
			{STATE13,8'h06}:next_state = STATE14;//6th byte DST_ADDRESS

			{STATE14,8'hFF}:next_state = STATE15;//1st byte SRC_ADDRESS
			{STATE15,8'hFE}:next_state = STATE16;//2nd byte SRC_ADDRESS
			{STATE16,8'hFD}:next_state = STATE17;//3rd byte SRC_ADDRESS
			{STATE17,8'hFC}:next_state = STATE18;//4th byte SRC_ADDRESS
			{STATE18,8'hFB}:next_state = STATE19;//5th byte SRC_ADDRESS
			{STATE19,8'hFA}:next_state = STATE20;//6th byte SRC_ADDRESS

			{STATE20,8'h08}:next_state = STATE21;//1st byte TYPE_LENGTH
			{STATE21,8'h00}:next_state = STATE22;//2nd byte TYPE_LENGTH

			default: next_state = STATE0; //anything Else -> start from begininng 
		endcase
	end
end

//SEQUENTIAL LOGIC
always @(posedge clock) begin //positive transition of clock 	
	if(reset == 1'b1) begin //synchronus active high reset
		state <= STATE0;
		preamble_valid <= 1'b0;
		dst_addr_valid <= 1'b0;
		src_addr_valid <= 1'b0;
		type_length_valid <= 1'b0;
	end
	else begin
		state = next_state; //blocking assignment to reflect in output immediately
		case(state)
			//STATE0 is equivilant to start (either during instantiation or failure during parsing)
			STATE0:begin
					preamble_valid <= 1'b0;
					dst_addr_valid <= 1'b0;
					src_addr_valid <= 1'b0;
					type_length_valid <= 1'b0;		
				end

			//STATE8 is equivilant to valid PREAMBLE received
			STATE8: begin
					preamble_valid <= 1'b1;
				end
			//STATE9 is equivilant to valid PREAMBLE received last posedge of clock
			STATE9:begin
					preamble_valid <= 1'b0;
				end

			//STATE14 is equivilant to valid DST_ADDRESS received
			STATE14: begin
					dst_addr_valid <= 1'b1;
				end
			//STATE9 is equivilant to valid DST_ADDRESS received last posedge of clock
			STATE15:begin
					dst_addr_valid <= 1'b0;
				end
			//STATE20 is equivilant to valid SRC_ADDRESS received
			STATE20: begin
					src_addr_valid <= 1'b1;
				end
			//STATE9 is equivilant to valid SRC_ADDRESS received last posedge of clock
			STATE21:begin
					src_addr_valid <= 1'b0;
				end
			//STATE8 is equivilant to valid TYPE_LENGTH received
			STATE22: begin
					type_length_valid <= 1'b1;
				end
		endcase		
	end
end

endmodule

control_fsm.v
/*
This module cotains the Ethernet Packet Detector implementation
of Cobinational and Sequential parts of the controller Logic.
*/
module control_fsm(
		input clock,
		input reset,
		input control,
		input [7:0] data,
		input type_length_valid,
		input packet_size_valid,
		output enable_header,
		output enable_payload
	);

//Inputs: all ACTIVE HIGH
wire clock, reset, control, 
	type_length_valid, packet_size_valid;
wire [7:0] data;

//Outputs: all ACTIVE HIGH
wire enable_header, enable_payload; //enable signals for header and payload modules

//3 states
parameter [1:0] STATE0 = 2'b00;
parameter [1:0] STATE1 = 2'b01;
parameter [1:0] STATE2 = 2'b10;

reg [1:0] state = STATE0;
reg [1:0] next_state = STATE0;

assign enable_header = control && !state;
assign enable_payload = control & state;

// always @(*) begin
// 	enable_header <= control && !state;
// 	enable_payload <= control & state;
// end

always @(type_length_valid or packet_size_valid) begin
	next_state = STATE0; //prevent unintended latches
	case(state)
		STATE0:begin
			next_state = STATE0;
			if(type_length_valid == 1'b1 && control == 1'b1)begin
				next_state = STATE1;
			end
		end
		STATE1:begin
			next_state = STATE1;
			if(packet_size_valid == 1'b1)begin
				next_state = STATE2;
			end
			// if(control == 1'b0)begin
			// 	next_state = STATE0;
			// end
		end
		STATE2:begin
			next_state = STATE2;
			if(control == 1'b0 && data == 8'h00)begin
				next_state = STATE0;
			end
		end
	endcase
end

always @(posedge clock) begin
	// reset and control are synchronus active high
	// if (reset == 1'b1 || control == 1'b0) begin
	// 	state <= STATE0;
	// end
	if (reset == 1'b1) begin // reset is synchronus active high
		state <= STATE0;
		// enable_header = 1'b1;
		// enable_payload = 1'b0;
	end
	else begin
		state = next_state; //blocking assignment
	end
end

endmodule

epd.v
/*
This module cotains the Ethernet Packet Detector implementation
of Cobinational and Sequential parts of the controller Logic.
*/
`include "header_fsm.v"
`include "payload_crc.v"
`include "control_fsm.v"

module epd(
		input clock,
		input reset,
		input [7:0] data,
		input control,
		output preamble_valid,
		output dst_addr_valid,
		output src_addr_valid,
		output type_length_valid,
		output packet_size_valid,
		output [3:0] valid_packet_counter 
	);

//Inputs: all ACTIVE HIGH
wire clock, reset, control;
wire [7:0] data;

//Outputs: all ACTIVE HIGH
wire preamble_valid, src_addr_valid, 
	dst_addr_valid, type_length_valid,
	packet_size_valid;
wire [3:0] valid_packet_counter;

control_fsm U_control_fsm(
clock,
reset,
control,
type_length_valid,
packet_size_valid,
enable_header,
enable_payload
);

header_fsm U_header_fsm(
.clock (clock),
.reset (reset),
.enable (enable_header),
.data (data),
.preamble_valid (preamble_valid),
.dst_addr_valid (dst_addr_valid),
.src_addr_valid (src_addr_valid),
.type_length_valid (type_length_valid)
);

payload_crc U_payload_crc(
.clock (clock),
.reset (reset),
.enable (enable_payload),
.packet_size_valid (packet_size_valid),
.valid_packet_counter (valid_packet_counter)
);

endmodule

tests/multiple_valid_packets_ifg_cntrl.v
// Test sends multiple valid packets with an invalid IFG (control is HIGH)
// between 2 of them.
`include "epd.v"

module multiple_valid_packets_ifg_cntrl;

reg clock, reset, control;
reg [7:0] data;

wire preamble_valid, dst_addr_valid, src_addr_valid,
	type_length_valid, packet_size_valid;
wire [3:0] valid_packet_counter;

epd U_epd(
clock,
reset,
data,
control,
preamble_valid,
dst_addr_valid,
src_addr_valid,
type_length_valid,
packet_size_valid,
valid_packet_counter 
);


initial begin
	$dumpfile("multiple_valid_packets_ifg_cntrl.vcd");
	$dumpvars(0,multiple_valid_packets_ifg_cntrl);
	
	clock = 1;
	
	control = 1;
	data = 0;
	reset = 0;
	// #4 reset = 0;
	
	//***************************** First packet ******************************
	//valid preamble
	repeat (7) #2 data = 8'h55;
	#2 data = 8'hD5;

	//valid DST
	#2 data = 8'h01; #2 data = 8'h02; #2 data = 8'h03; #2 data = 8'h04;
    #2 data = 8'h05; #2 data = 8'h06;

    //valid SRC
    #2 data = 8'hFF; #2 data = 8'hFE; #2 data = 8'hFD; #2 data = 8'hFC;
    #2 data = 8'hFB; #2 data = 8'hFA;

	//valid type_length
	#2 data = 8'h08; #2 data = 8'h00;

	//send payload and crc
	repeat (49) #2 data = 8'h55;#2 data = 8'hFF;

	//send one IFG
	#2 control = 0;
    data = 8'h00;
    #2 control = 1;

    //***************************** Second packet ******************************
	//valid preamble
	repeat (7) #2 data = 8'h55;
	#2 data = 8'hD5;

	//valid DST
	#2 data = 8'h01; #2 data = 8'h02; #2 data = 8'h03; #2 data = 8'h04;
    #2 data = 8'h05; #2 data = 8'h06;

    //valid SRC
    #2 data = 8'hFF; #2 data = 8'hFE; #2 data = 8'hFD; #2 data = 8'hFC;
    #2 data = 8'hFB; #2 data = 8'hFA;

	//valid type_length
	#2 data = 8'h08; #2 data = 8'h00;

	//send payload and crc
	repeat (49) #2 data = 8'h55;#2 data = 8'h56;

	//send multiple IFGs
	#2 control = 1; //CONTROL IS HIGH DURING IFG (INVALID IFG)
    data = 8'h00;
    #6 control = 1;

    //***************************** Third packet ******************************
	//valid preamble
	repeat (7) #2 data = 8'h55;
	#2 data = 8'hD5;

	//valid DST
	#2 data = 8'h01; #2 data = 8'h02; #2 data = 8'h03; #2 data = 8'h04;
    #2 data = 8'h05; #2 data = 8'h06;

    //valid SRC
    #2 data = 8'hFF; #2 data = 8'hFE; #2 data = 8'hFD; #2 data = 8'hFC;
    #2 data = 8'hFB; #2 data = 8'hFA;

	//valid type_length
	#2 data = 8'h08; #2 data = 8'h00;

	//send payload and crc
	repeat (49) #2 data = 8'h55;#2 data = 8'h56;

	//send one IFG
	#2 control = 0;
    data = 8'h00;
    #2 control = 1;

    //***************************** Fourth packet ******************************
	//valid preamble
	repeat (7) #2 data = 8'h55;
	#2 data = 8'hD5;

	//valid DST
	#2 data = 8'h01; #2 data = 8'h02; #2 data = 8'h03; #2 data = 8'h04;
    #2 data = 8'h05; #2 data = 8'h06;

    //valid SRC
    #2 data = 8'hFF; #2 data = 8'hFE; #2 data = 8'hFD; #2 data = 8'hFC;
    #2 data = 8'hFB; #2 data = 8'hFA;

	//valid type_length
	#2 data = 8'h08; #2 data = 8'h00;

	//send payload and crc
	repeat (49) #2 data = 8'h55;#2 data = 8'h56;

	//send one IFG
	#2 control = 0;
    data = 8'h00;
    #2 control = 1;


    #10 $finish;
end


//clock generator
always
	#1 clock =~ clock;

endmodule

tests/multiple_valid_packets_ifg_cntrl.vcd
$date
	Wed Mar  1 07:49:07 2017
$end
$version
	Icarus Verilog
$end
$timescale
	1s
$end
$scope module multiple_valid_packets_ifg_cntrl $end
$var wire 1 ! dst_addr_valid $end
$var wire 1 " packet_size_valid $end
$var wire 1 # preamble_valid $end
$var wire 1 $ src_addr_valid $end
$var wire 1 % type_length_valid $end
$var wire 4 & valid_packet_counter [3:0] $end
$var reg 1 ' clock $end
$var reg 1 ( control $end
$var reg 8 ) data [7:0] $end
$var reg 1 * reset $end
$scope module U_epd $end
$var wire 1 + clock $end
$var wire 1 , control $end
$var wire 8 - data [7:0] $end
$var wire 1 ! dst_addr_valid $end
$var wire 1 . enable_header $end
$var wire 1 / enable_payload $end
$var wire 1 " packet_size_valid $end
$var wire 1 # preamble_valid $end
$var wire 1 0 reset $end
$var wire 1 $ src_addr_valid $end
$var wire 1 % type_length_valid $end
$var wire 4 1 valid_packet_counter [3:0] $end
$scope module U_control_fsm $end
$var wire 1 + clock $end
$var wire 1 , control $end
$var wire 8 2 data [7:0] $end
$var wire 1 . enable_header $end
$var wire 1 / enable_payload $end
$var wire 1 " packet_size_valid $end
$var wire 1 0 reset $end
$var wire 1 % type_length_valid $end
$var reg 2 3 next_state [1:0] $end
$var reg 2 4 state [1:0] $end
$upscope $end
$scope module U_header_fsm $end
$var wire 1 + clock $end
$var wire 8 5 data [7:0] $end
$var wire 1 . enable $end
$var wire 1 0 reset $end
$var reg 1 6 dst_addr_valid $end
$var reg 5 7 next_state [4:0] $end
$var reg 1 8 preamble_valid $end
$var reg 1 9 src_addr_valid $end
$var reg 5 : state [4:0] $end
$var reg 1 ; type_length_valid $end
$upscope $end
$scope module U_payload_crc $end
$var wire 1 + clock $end
$var wire 1 / enable $end
$var wire 1 0 reset $end
$var reg 6 < bytes_counter [5:0] $end
$var reg 1 = packet_size_valid $end
$var reg 4 > valid_packet_counter [3:0] $end
$upscope $end
$upscope $end
$upscope $end
$enddefinitions $end
#0
$dumpvars
b0 >
x=
bx <
0;
b0 :
09
08
b0 7
06
b0 5
b0 4
b0 3
b0 2
b0 1
00
0/
1.
b0 -
1,
1+
0*
b0 )
1(
1'
b0 &
0%
0$
0#
x"
0!
$end
#1
0'
0+
#2
0=
0"
b1 <
b1 :
b10 7
1'
1+
b1010101 )
b1010101 -
b1010101 2
b1010101 5
#3
0'
0+
#4
b11 7
b10 :
1'
1+
#5
0'
0+
#6
b100 7
b11 :
1'
1+
#7
0'
0+
#8
b101 7
b100 :
1'
1+
#9
0'
0+
#10
b110 7
b101 :
1'
1+
#11
0'
0+
#12
b111 7
b110 :
1'
1+
#13
0'
0+
#14
b0 7
b111 :
1'
1+
#15
0'
0+
#16
18
1#
b1000 :
b0 7
1'
1+
b11010101 )
b11010101 -
b11010101 2
b11010101 5
#17
0'
0+
#18
08
0#
b1001 :
b0 7
1'
1+
b1 )
b1 -
b1 2
b1 5
#19
0'
0+
#20
b1010 :
b0 7
1'
1+
b10 )
b10 -
b10 2
b10 5
#21
0'
0+
#22
b1011 :
b0 7
1'
1+
b11 )
b11 -
b11 2
b11 5
#23
0'
0+
#24
b1100 :
b0 7
1'
1+
b100 )
b100 -
b100 2
b100 5
#25
0'
0+
#26
b1101 :
b0 7
1'
1+
b101 )
b101 -
b101 2
b101 5
#27
0'
0+
#28
16
1!
b1110 :
b0 7
1'
1+
b110 )
b110 -
b110 2
b110 5
#29
0'
0+
#30
06
0!
b1111 :
b0 7
1'
1+
b11111111 )
b11111111 -
b11111111 2
b11111111 5
#31
0'
0+
#32
b10000 :
b0 7
1'
1+
b11111110 )
b11111110 -
b11111110 2
b11111110 5
#33
0'
0+
#34
b10001 :
b0 7
1'
1+
b11111101 )
b11111101 -
b11111101 2
b11111101 5
#35
0'
0+
#36
b10010 :
b0 7
1'
1+
b11111100 )
b11111100 -
b11111100 2
b11111100 5
#37
0'
0+
#38
b10011 :
b0 7
1'
1+
b11111011 )
b11111011 -
b11111011 2
b11111011 5
#39
0'
0+
#40
19
1$
b10100 :
b0 7
1'
1+
b11111010 )
b11111010 -
b11111010 2
b11111010 5
#41
0'
0+
#42
09
0$
b10101 :
b0 7
1'
1+
b1000 )
b1000 -
b1000 2
b1000 5
#43
0'
0+
#44
b1 3
1;
1%
b10110 :
b0 7
1'
1+
b0 )
b0 -
b0 2
b0 5
#45
0'
0+
#46
0;
0%
1/
b1 3
0.
b0 :
b1 4
1'
1+
b1010101 )
b1010101 -
b1010101 2
b1010101 5
#47
0'
0+
#48
b10 <
1'
1+
#49
0'
0+
#50
b11 <
1'
1+
#51
0'
0+
#52
b100 <
1'
1+
#53
0'
0+
#54
b101 <
1'
1+
#55
0'
0+
#56
b110 <
1'
1+
#57
0'
0+
#58
b111 <
1'
1+
#59
0'
0+
#60
b1000 <
1'
1+
#61
0'
0+
#62
b1001 <
1'
1+
#63
0'
0+
#64
b1010 <
1'
1+
#65
0'
0+
#66
b1011 <
1'
1+
#67
0'
0+
#68
b1100 <
1'
1+
#69
0'
0+
#70
b1101 <
1'
1+
#71
0'
0+
#72
b1110 <
1'
1+
#73
0'
0+
#74
b1111 <
1'
1+
#75
0'
0+
#76
b10000 <
1'
1+
#77
0'
0+
#78
b10001 <
1'
1+
#79
0'
0+
#80
b10010 <
1'
1+
#81
0'
0+
#82
b10011 <
1'
1+
#83
0'
0+
#84
b10100 <
1'
1+
#85
0'
0+
#86
b10101 <
1'
1+
#87
0'
0+
#88
b10110 <
1'
1+
#89
0'
0+
#90
b10111 <
1'
1+
#91
0'
0+
#92
b11000 <
1'
1+
#93
0'
0+
#94
b11001 <
1'
1+
#95
0'
0+
#96
b11010 <
1'
1+
#97
0'
0+
#98
b11011 <
1'
1+
#99
0'
0+
#100
b11100 <
1'
1+
#101
0'
0+
#102
b11101 <
1'
1+
#103
0'
0+
#104
b11110 <
1'
1+
#105
0'
0+
#106
b11111 <
1'
1+
#107
0'
0+
#108
b100000 <
1'
1+
#109
0'
0+
#110
b100001 <
1'
1+
#111
0'
0+
#112
b100010 <
1'
1+
#113
0'
0+
#114
b100011 <
1'
1+
#115
0'
0+
#116
b100100 <
1'
1+
#117
0'
0+
#118
b100101 <
1'
1+
#119
0'
0+
#120
b100110 <
1'
1+
#121
0'
0+
#122
b100111 <
1'
1+
#123
0'
0+
#124
b101000 <
1'
1+
#125
0'
0+
#126
b101001 <
1'
1+
#127
0'
0+
#128
b101010 <
1'
1+
#129
0'
0+
#130
b101011 <
1'
1+
#131
0'
0+
#132
b101100 <
1'
1+
#133
0'
0+
#134
b101101 <
1'
1+
#135
0'
0+
#136
b101110 <
1'
1+
#137
0'
0+
#138
b101111 <
1'
1+
#139
0'
0+
#140
b110000 <
1'
1+
#141
0'
0+
#142
b110001 <
1'
1+
#143
0'
0+
#144
b10 3
b1 >
b1 &
b1 1
1=
1"
b110010 <
1'
1+
b11111111 )
b11111111 -
b11111111 2
b11111111 5
#145
0'
0+
#146
0=
0"
b0 3
0/
b110011 <
b0 4
1'
1+
b0 )
b0 -
b0 2
b0 5
0(
0,
#147
0'
0+
#148
b1 <
1.
1'
1+
1(
1,
#149
0'
0+
#150
b1 :
b10 7
1'
1+
b1010101 )
b1010101 -
b1010101 2
b1010101 5
#151
0'
0+
#152
b11 7
b10 :
1'
1+
#153
0'
0+
#154
b100 7
b11 :
1'
1+
#155
0'
0+
#156
b101 7
b100 :
1'
1+
#157
0'
0+
#158
b110 7
b101 :
1'
1+
#159
0'
0+
#160
b111 7
b110 :
1'
1+
#161
0'
0+
#162
b0 7
b111 :
1'
1+
#163
0'
0+
#164
18
1#
b1000 :
b0 7
1'
1+
b11010101 )
b11010101 -
b11010101 2
b11010101 5
#165
0'
0+
#166
08
0#
b1001 :
b0 7
1'
1+
b1 )
b1 -
b1 2
b1 5
#167
0'
0+
#168
b1010 :
b0 7
1'
1+
b10 )
b10 -
b10 2
b10 5
#169
0'
0+
#170
b1011 :
b0 7
1'
1+
b11 )
b11 -
b11 2
b11 5
#171
0'
0+
#172
b1100 :
b0 7
1'
1+
b100 )
b100 -
b100 2
b100 5
#173
0'
0+
#174
b1101 :
b0 7
1'
1+
b101 )
b101 -
b101 2
b101 5
#175
0'
0+
#176
16
1!
b1110 :
b0 7
1'
1+
b110 )
b110 -
b110 2
b110 5
#177
0'
0+
#178
06
0!
b1111 :
b0 7
1'
1+
b11111111 )
b11111111 -
b11111111 2
b11111111 5
#179
0'
0+
#180
b10000 :
b0 7
1'
1+
b11111110 )
b11111110 -
b11111110 2
b11111110 5
#181
0'
0+
#182
b10001 :
b0 7
1'
1+
b11111101 )
b11111101 -
b11111101 2
b11111101 5
#183
0'
0+
#184
b10010 :
b0 7
1'
1+
b11111100 )
b11111100 -
b11111100 2
b11111100 5
#185
0'
0+
#186
b10011 :
b0 7
1'
1+
b11111011 )
b11111011 -
b11111011 2
b11111011 5
#187
0'
0+
#188
19
1$
b10100 :
b0 7
1'
1+
b11111010 )
b11111010 -
b11111010 2
b11111010 5
#189
0'
0+
#190
09
0$
b10101 :
b0 7
1'
1+
b1000 )
b1000 -
b1000 2
b1000 5
#191
0'
0+
#192
b1 3
1;
1%
b10110 :
b0 7
1'
1+
b0 )
b0 -
b0 2
b0 5
#193
0'
0+
#194
0;
0%
1/
b1 3
0.
b0 :
b1 4
1'
1+
b1010101 )
b1010101 -
b1010101 2
b1010101 5
#195
0'
0+
#196
b10 <
1'
1+
#197
0'
0+
#198
b11 <
1'
1+
#199
0'
0+
#200
b100 <
1'
1+
#201
0'
0+
#202
b101 <
1'
1+
#203
0'
0+
#204
b110 <
1'
1+
#205
0'
0+
#206
b111 <
1'
1+
#207
0'
0+
#208
b1000 <
1'
1+
#209
0'
0+
#210
b1001 <
1'
1+
#211
0'
0+
#212
b1010 <
1'
1+
#213
0'
0+
#214
b1011 <
1'
1+
#215
0'
0+
#216
b1100 <
1'
1+
#217
0'
0+
#218
b1101 <
1'
1+
#219
0'
0+
#220
b1110 <
1'
1+
#221
0'
0+
#222
b1111 <
1'
1+
#223
0'
0+
#224
b10000 <
1'
1+
#225
0'
0+
#226
b10001 <
1'
1+
#227
0'
0+
#228
b10010 <
1'
1+
#229
0'
0+
#230
b10011 <
1'
1+
#231
0'
0+
#232
b10100 <
1'
1+
#233
0'
0+
#234
b10101 <
1'
1+
#235
0'
0+
#236
b10110 <
1'
1+
#237
0'
0+
#238
b10111 <
1'
1+
#239
0'
0+
#240
b11000 <
1'
1+
#241
0'
0+
#242
b11001 <
1'
1+
#243
0'
0+
#244
b11010 <
1'
1+
#245
0'
0+
#246
b11011 <
1'
1+
#247
0'
0+
#248
b11100 <
1'
1+
#249
0'
0+
#250
b11101 <
1'
1+
#251
0'
0+
#252
b11110 <
1'
1+
#253
0'
0+
#254
b11111 <
1'
1+
#255
0'
0+
#256
b100000 <
1'
1+
#257
0'
0+
#258
b100001 <
1'
1+
#259
0'
0+
#260
b100010 <
1'
1+
#261
0'
0+
#262
b100011 <
1'
1+
#263
0'
0+
#264
b100100 <
1'
1+
#265
0'
0+
#266
b100101 <
1'
1+
#267
0'
0+
#268
b100110 <
1'
1+
#269
0'
0+
#270
b100111 <
1'
1+
#271
0'
0+
#272
b101000 <
1'
1+
#273
0'
0+
#274
b101001 <
1'
1+
#275
0'
0+
#276
b101010 <
1'
1+
#277
0'
0+
#278
b101011 <
1'
1+
#279
0'
0+
#280
b101100 <
1'
1+
#281
0'
0+
#282
b101101 <
1'
1+
#283
0'
0+
#284
b101110 <
1'
1+
#285
0'
0+
#286
b101111 <
1'
1+
#287
0'
0+
#288
b110000 <
1'
1+
#289
0'
0+
#290
b110001 <
1'
1+
#291
0'
0+
#292
b10 3
b10 >
b10 &
b10 1
1=
1"
b110010 <
1'
1+
b1010110 )
b1010110 -
b1010110 2
b1010110 5
#293
0'
0+
#294
0=
0"
0/
b10 3
b110011 <
b10 4
1'
1+
b0 )
b0 -
b0 2
b0 5
#295
0'
0+
#296
b1 <
1'
1+
#297
0'
0+
#298
1'
1+
#299
0'
0+
#300
1'
1+
#301
0'
0+
#302
1'
1+
b1010101 )
b1010101 -
b1010101 2
b1010101 5
#303
0'
0+
#304
1'
1+
#305
0'
0+
#306
1'
1+
#307
0'
0+
#308
1'
1+
#309
0'
0+
#310
1'
1+
#311
0'
0+
#312
1'
1+
#313
0'
0+
#314
1'
1+
#315
0'
0+
#316
1'
1+
b11010101 )
b11010101 -
b11010101 2
b11010101 5
#317
0'
0+
#318
1'
1+
b1 )
b1 -
b1 2
b1 5
#319
0'
0+
#320
1'
1+
b10 )
b10 -
b10 2
b10 5
#321
0'
0+
#322
1'
1+
b11 )
b11 -
b11 2
b11 5
#323
0'
0+
#324
1'
1+
b100 )
b100 -
b100 2
b100 5
#325
0'
0+
#326
1'
1+
b101 )
b101 -
b101 2
b101 5
#327
0'
0+
#328
1'
1+
b110 )
b110 -
b110 2
b110 5
#329
0'
0+
#330
1'
1+
b11111111 )
b11111111 -
b11111111 2
b11111111 5
#331
0'
0+
#332
1'
1+
b11111110 )
b11111110 -
b11111110 2
b11111110 5
#333
0'
0+
#334
1'
1+
b11111101 )
b11111101 -
b11111101 2
b11111101 5
#335
0'
0+
#336
1'
1+
b11111100 )
b11111100 -
b11111100 2
b11111100 5
#337
0'
0+
#338
1'
1+
b11111011 )
b11111011 -
b11111011 2
b11111011 5
#339
0'
0+
#340
1'
1+
b11111010 )
b11111010 -
b11111010 2
b11111010 5
#341
0'
0+
#342
1'
1+
b1000 )
b1000 -
b1000 2
b1000 5
#343
0'
0+
#344
1'
1+
b0 )
b0 -
b0 2
b0 5
#345
0'
0+
#346
1'
1+
b1010101 )
b1010101 -
b1010101 2
b1010101 5
