payload_crc.v
/*
This Module implements the parsing Moore FSM of Payload and CRC Fields.
Since no validation is required, parsing of Payload and CRC problem 
reduces to a counter that counts 50 bytes.
*/
module payload_crc(
		input clock,
		input reset,
		input enable,
		output packet_size_valid,
		output [3:0] valid_packet_counter
	);

//Inputs: all ACTIVE HIGH
wire clock, enable, reset;

//Output: all ACTIVE HIGH
reg packet_size_valid;
reg [3:0] valid_packet_counter;

//Counter
reg [5:0] bytes_counter;

always @(enable) begin
	if(enable == 1'b0)begin
		bytes_counter <= 1;
		packet_size_valid <= 1'b0;
	end
end

always @(posedge clock) begin
	if(reset == 1'b1) begin //synchronus active high reset
		bytes_counter <= 1'b0;
		packet_size_valid <= 1'b0;
		valid_packet_counter <= 4'b0;
	end
	// if (enable == 1'b0) begin
	// 	bytes_counter <= 1;
	// 	packet_size_valid <= 1'b0;
	// end 
	else begin
		bytes_counter = bytes_counter + 1; 
		if (bytes_counter == 50) begin
			packet_size_valid <= 1'b1;
			valid_packet_counter <= valid_packet_counter + 1; 
		end
	end
end

endmodule

header_fsm.v
/*
This Module implements the parsing Moore FSM of Ethernet Header Fields 
*/
module header_fsm(
		input clock,
		input reset,
		input enable,
		input [7:0] data,
		output preamble_valid,
		output dst_addr_valid,
		output src_addr_valid,
		output type_length_valid
	);

//Inputs: all ACTIVE HIGH
wire [7:0] data;
wire clock, enable;

//Outputs: all ACTIVE HIGH
reg preamble_valid, dst_addr_valid
	, src_addr_valid, type_length_valid;

parameter [4:0] STATE0  = 5'b00000;
parameter [4:0] STATE1  = 5'b00001;
parameter [4:0] STATE2  = 5'b00010;
parameter [4:0] STATE3  = 5'b00011;
parameter [4:0] STATE4  = 5'b00100;
parameter [4:0] STATE5  = 5'b00101;
parameter [4:0] STATE6  = 5'b00110;
parameter [4:0] STATE7  = 5'b00111;
parameter [4:0] STATE8  = 5'b01000;
parameter [4:0] STATE9  = 5'b01001;
parameter [4:0] STATE10 = 5'b01010;
parameter [4:0] STATE11 = 5'b01011;
parameter [4:0] STATE12 = 5'b01100;
parameter [4:0] STATE13 = 5'b01101;
parameter [4:0] STATE14 = 5'b01110;
parameter [4:0] STATE15 = 5'b01111;
parameter [4:0] STATE16 = 5'b10000;
parameter [4:0] STATE17 = 5'b10001;
parameter [4:0] STATE18 = 5'b10010;
parameter [4:0] STATE19 = 5'b10011;
parameter [4:0] STATE20 = 5'b10100;
parameter [4:0] STATE21 = 5'b10101;
parameter [4:0] STATE22 = 5'b10110;

//23 states
reg [4:0] state = STATE0;
reg [4:0] next_state = STATE0;


//COMBINATIONAL LOGIC
always @(state or data or enable) begin
	next_state = 0; //prevent latches
	if (enable == 1'b1) begin
		case({state,data}) 
			{STATE0,8'h55}:next_state = STATE1;//1st byte PREAMBLE
			{STATE1,8'h55}:next_state = STATE2;//2nd byte PREAMBLE
			{STATE2,8'h55}:next_state = STATE3;//3rd byte PREAMBLE
			{STATE3,8'h55}:next_state = STATE4;//4th byte PREAMBLE
			{STATE4,8'h55}:next_state = STATE5;//5th byte PREAMBLE
			{STATE5,8'h55}:next_state = STATE6;//6th byte PREAMBLE
			{STATE6,8'h55}:next_state = STATE7;//7th byte PREAMBLE
			{STATE7,8'hD5}:next_state = STATE8;//8th byte PREAMBLE			
			
			{STATE8,8'h01}:next_state = STATE9;//1st byte DST_ADDRESS
			{STATE9,8'h02}:next_state = STATE10;//2nd byte DST_ADDRESS
			{STATE10,8'h03}:next_state = STATE11;//3rd byte DST_ADDRESS
			{STATE11,8'h04}:next_state = STATE12;//4th byte DST_ADDRESS
			{STATE12,8'h05}:next_state = STATE13;//5th byte DST_ADDRESS
			{STATE13,8'h06}:next_state = STATE14;//6th byte DST_ADDRESS

			{STATE14,8'hFF}:next_state = STATE15;//1st byte SRC_ADDRESS
			{STATE15,8'hFE}:next_state = STATE16;//2nd byte SRC_ADDRESS
			{STATE16,8'hFD}:next_state = STATE17;//3rd byte SRC_ADDRESS
			{STATE17,8'hFC}:next_state = STATE18;//4th byte SRC_ADDRESS
			{STATE18,8'hFB}:next_state = STATE19;//5th byte SRC_ADDRESS
			{STATE19,8'hFA}:next_state = STATE20;//6th byte SRC_ADDRESS

			{STATE20,8'h08}:next_state = STATE21;//1st byte TYPE_LENGTH
			{STATE21,8'h00}:next_state = STATE22;//2nd byte TYPE_LENGTH

			default: next_state = STATE0; //anything Else -> start from begininng 
		endcase
	end
end

//SEQUENTIAL LOGIC
always @(posedge clock) begin //positive transition of clock 	
	if(reset == 1'b1) begin //synchronus active high reset
		state <= STATE0;
		preamble_valid <= 1'b0;
		dst_addr_valid <= 1'b0;
		src_addr_valid <= 1'b0;
		type_length_valid <= 1'b0;
	end
	else begin
		state = next_state; //blocking assignment to reflect in output immediately
		case(state)
			//STATE0 is equivilant to start (either during instantiation or failure during parsing)
			STATE0:begin
					preamble_valid <= 1'b0;
					dst_addr_valid <= 1'b0;
					src_addr_valid <= 1'b0;
					type_length_valid <= 1'b0;		
				end

			//STATE8 is equivilant to valid PREAMBLE received
			STATE8: begin
					preamble_valid <= 1'b1;
				end
			//STATE9 is equivilant to valid PREAMBLE received last posedge of clock
			STATE9:begin
					preamble_valid <= 1'b0;
				end

			//STATE14 is equivilant to valid DST_ADDRESS received
			STATE14: begin
					dst_addr_valid <= 1'b1;
				end
			//STATE9 is equivilant to valid DST_ADDRESS received last posedge of clock
			STATE15:begin
					dst_addr_valid <= 1'b0;
				end
			//STATE20 is equivilant to valid SRC_ADDRESS received
			STATE20: begin
					src_addr_valid <= 1'b1;
				end
			//STATE9 is equivilant to valid SRC_ADDRESS received last posedge of clock
			STATE21:begin
					src_addr_valid <= 1'b0;
				end
			//STATE8 is equivilant to valid TYPE_LENGTH received
			STATE22: begin
					type_length_valid <= 1'b1;
				end
		endcase		
	end
end

endmodule

control_fsm.v
/*
This module cotains the Ethernet Packet Detector implementation
of Cobinational and Sequential parts of the controller Logic.
*/
module control_fsm(
		input clock,
		input reset,
		input control,
		input [7:0] data,
		input type_length_valid,
		input packet_size_valid,
		output enable_header,
		output enable_payload
	);

//Inputs: all ACTIVE HIGH
wire clock, reset, control, 
	type_length_valid, packet_size_valid;
wire [7:0] data;

//Outputs: all ACTIVE HIGH
wire enable_header, enable_payload; //enable signals for header and payload modules

//3 states
parameter [1:0] STATE0 = 2'b00;
parameter [1:0] STATE1 = 2'b01;
parameter [1:0] STATE2 = 2'b10;

reg [1:0] state = STATE0;
reg [1:0] next_state = STATE0;

assign enable_header = control && !state;
assign enable_payload = control & state;

// always @(*) begin
// 	enable_header <= control && !state;
// 	enable_payload <= control & state;
// end

always @(type_length_valid or packet_size_valid) begin
	next_state = STATE0; //prevent unintended latches
	case(state)
		STATE0:begin
			next_state = STATE0;
			if(type_length_valid == 1'b1 && control == 1'b1)begin
				next_state = STATE1;
			end
		end
		STATE1:begin
			next_state = STATE1;
			if(packet_size_valid == 1'b1)begin
				next_state = STATE2;
			end
			// if(control == 1'b0)begin
			// 	next_state = STATE0;
			// end
		end
		STATE2:begin
			next_state = STATE2;
			if(control == 1'b0 && data == 8'h00)begin
				next_state = STATE0;
			end
		end
	endcase
end

always @(posedge clock) begin
	// reset and control are synchronus active high
	// if (reset == 1'b1 || control == 1'b0) begin
	// 	state <= STATE0;
	// end
	if (reset == 1'b1) begin // reset is synchronus active high
		state <= STATE0;
		// enable_header = 1'b1;
		// enable_payload = 1'b0;
	end
	else begin
		state = next_state; //blocking assignment
	end
end

endmodule

epd.v
/*
This module cotains the Ethernet Packet Detector implementation
of Cobinational and Sequential parts of the controller Logic.
*/
`include "header_fsm.v"
`include "payload_crc.v"
`include "control_fsm.v"

module epd(
		input clock,
		input reset,
		input [7:0] data,
		input control,
		output preamble_valid,
		output dst_addr_valid,
		output src_addr_valid,
		output type_length_valid,
		output packet_size_valid,
		output [3:0] valid_packet_counter 
	);

//Inputs: all ACTIVE HIGH
wire clock, reset, control;
wire [7:0] data;

//Outputs: all ACTIVE HIGH
wire preamble_valid, src_addr_valid, 
	dst_addr_valid, type_length_valid,
	packet_size_valid;
wire [3:0] valid_packet_counter;

control_fsm U_control_fsm(
clock,
reset,
control,
type_length_valid,
packet_size_valid,
enable_header,
enable_payload
);

header_fsm U_header_fsm(
.clock (clock),
.reset (reset),
.enable (enable_header),
.data (data),
.preamble_valid (preamble_valid),
.dst_addr_valid (dst_addr_valid),
.src_addr_valid (src_addr_valid),
.type_length_valid (type_length_valid)
);

payload_crc U_payload_crc(
.clock (clock),
.reset (reset),
.enable (enable_payload),
.packet_size_valid (packet_size_valid),
.valid_packet_counter (valid_packet_counter)
);

endmodule

tests/one_valid_packet_hdr_rst.v
// Test triggers reset during sending header of 1 valid packet
`include "epd.v"

module one_valid_packet_hdr_rst;

reg clock, reset, control;
reg [7:0] data;

wire preamble_valid, dst_addr_valid, src_addr_valid,
	type_length_valid, packet_size_valid;
wire [3:0] valid_packet_counter;

epd U_epd(
clock,
reset,
data,
control,
preamble_valid,
dst_addr_valid,
src_addr_valid,
type_length_valid,
packet_size_valid,
valid_packet_counter 
);


initial begin
	$dumpfile("one_valid_packet_hdr_rst.vcd");
	$dumpvars(0,one_valid_packet_hdr_rst);
	
	clock = 0;
	
	control = 1;
	data = 0;
	reset = 0;
	
	//***************************** First packet ******************************
	//valid preamble
	repeat (7) #2 data = 8'h55;
	#2 data = 8'hD5;

	//valid DST
	#2 data = 8'h01; #2 data = 8'h02; #2 data = 8'h03; #2 data = 8'h04;
    #2 data = 8'h05; #2 data = 8'h06;

    #2 reset = 1;//TRIGGERING RESET DURING HEADER
    #2 reset = 0;

    //valid SRC
    #2 data = 8'hFF; #2 data = 8'hFE; #2 data = 8'hFD; #2 data = 8'hFC;
    #2 data = 8'hFB; #2 data = 8'hFA;

	//valid type_length
	#2 data = 8'h08; #2 data = 8'h00;

	//send payload and crc
	repeat (49) #2 data = 8'h55;#2 data = 8'h56;
    
	//send one IFG
	#2 control = 0;
    data = 8'h00;
    #2 control = 1;

    #10 $finish;
end


//clock generator
always
	#1 clock =~ clock;

endmodule

tests/one_valid_packet_hdr_rst.vcd
$date
	Wed Mar  1 07:49:37 2017
$end
$version
	Icarus Verilog
$end
$timescale
	1s
$end
$scope module one_valid_packet_hdr_rst $end
$var wire 1 ! dst_addr_valid $end
$var wire 1 " packet_size_valid $end
$var wire 1 # preamble_valid $end
$var wire 1 $ src_addr_valid $end
$var wire 1 % type_length_valid $end
$var wire 4 & valid_packet_counter [3:0] $end
$var reg 1 ' clock $end
$var reg 1 ( control $end
$var reg 8 ) data [7:0] $end
$var reg 1 * reset $end
$scope module U_epd $end
$var wire 1 + clock $end
$var wire 1 , control $end
$var wire 8 - data [7:0] $end
$var wire 1 ! dst_addr_valid $end
$var wire 1 . enable_header $end
$var wire 1 / enable_payload $end
$var wire 1 " packet_size_valid $end
$var wire 1 # preamble_valid $end
$var wire 1 0 reset $end
$var wire 1 $ src_addr_valid $end
$var wire 1 % type_length_valid $end
$var wire 4 1 valid_packet_counter [3:0] $end
$scope module U_control_fsm $end
$var wire 1 + clock $end
$var wire 1 , control $end
$var wire 8 2 data [7:0] $end
$var wire 1 . enable_header $end
$var wire 1 / enable_payload $end
$var wire 1 " packet_size_valid $end
$var wire 1 0 reset $end
$var wire 1 % type_length_valid $end
$var reg 2 3 next_state [1:0] $end
$var reg 2 4 state [1:0] $end
$upscope $end
$scope module U_header_fsm $end
$var wire 1 + clock $end
$var wire 8 5 data [7:0] $end
$var wire 1 . enable $end
$var wire 1 0 reset $end
$var reg 1 6 dst_addr_valid $end
$var reg 5 7 next_state [4:0] $end
$var reg 1 8 preamble_valid $end
$var reg 1 9 src_addr_valid $end
$var reg 5 : state [4:0] $end
$var reg 1 ; type_length_valid $end
$upscope $end
$scope module U_payload_crc $end
$var wire 1 + clock $end
$var wire 1 / enable $end
$var wire 1 0 reset $end
$var reg 6 < bytes_counter [5:0] $end
$var reg 1 = packet_size_valid $end
$var reg 4 > valid_packet_counter [3:0] $end
$upscope $end
$upscope $end
$upscope $end
$enddefinitions $end
#0
$dumpvars
b0 >
x=
bx <
x;
b0 :
x9
x8
b0 7
x6
b0 5
b0 4
b0 3
b0 2
b0 1
00
0/
1.
b0 -
1,
0+
0*
b0 )
1(
0'
b0 &
x%
x$
x#
x"
x!
$end
#1
0;
0%
09
0$
06
0!
08
0#
0=
0"
b1 <
1'
1+
#2
b1 7
0'
0+
b1010101 )
b1010101 -
b1010101 2
b1010101 5
#3
b10 7
b1 :
1'
1+
#4
0'
0+
#5
b11 7
b10 :
1'
1+
#6
0'
0+
#7
b100 7
b11 :
1'
1+
#8
0'
0+
#9
b101 7
b100 :
1'
1+
#10
0'
0+
#11
b110 7
b101 :
1'
1+
#12
0'
0+
#13
b111 7
b110 :
1'
1+
#14
0'
0+
#15
b0 7
b111 :
1'
1+
#16
b1000 7
0'
0+
b11010101 )
b11010101 -
b11010101 2
b11010101 5
#17
18
1#
b0 7
b1000 :
1'
1+
#18
b1001 7
0'
0+
b1 )
b1 -
b1 2
b1 5
#19
08
0#
b0 7
b1001 :
1'
1+
#20
b1010 7
0'
0+
b10 )
b10 -
b10 2
b10 5
#21
b0 7
b1010 :
1'
1+
#22
b1011 7
0'
0+
b11 )
b11 -
b11 2
b11 5
#23
b0 7
b1011 :
1'
1+
#24
b1100 7
0'
0+
b100 )
b100 -
b100 2
b100 5
#25
b0 7
b1100 :
1'
1+
#26
b1101 7
0'
0+
b101 )
b101 -
b101 2
b101 5
#27
b0 7
b1101 :
1'
1+
#28
b1110 7
0'
0+
b110 )
b110 -
b110 2
b110 5
#29
16
1!
b0 7
b1110 :
1'
1+
#30
0'
0+
1*
10
#31
b1 <
06
0!
b0 :
1'
1+
#32
0'
0+
0*
00
#33
1'
1+
#34
0'
0+
b11111111 )
b11111111 -
b11111111 2
b11111111 5
#35
1'
1+
#36
0'
0+
b11111110 )
b11111110 -
b11111110 2
b11111110 5
#37
1'
1+
#38
0'
0+
b11111101 )
b11111101 -
b11111101 2
b11111101 5
#39
1'
1+
#40
0'
0+
b11111100 )
b11111100 -
b11111100 2
b11111100 5
#41
1'
1+
#42
0'
0+
b11111011 )
b11111011 -
b11111011 2
b11111011 5
#43
1'
1+
#44
0'
0+
b11111010 )
b11111010 -
b11111010 2
b11111010 5
#45
1'
1+
#46
0'
0+
b1000 )
b1000 -
b1000 2
b1000 5
#47
1'
1+
#48
0'
0+
b0 )
b0 -
b0 2
b0 5
#49
1'
1+
#50
b1 7
0'
0+
b1010101 )
b1010101 -
b1010101 2
b1010101 5
#51
b10 7
b1 :
1'
1+
#52
0'
0+
#53
b11 7
b10 :
1'
1+
#54
0'
0+
#55
b100 7
b11 :
1'
1+
#56
0'
0+
#57
b101 7
b100 :
1'
1+
#58
0'
0+
#59
b110 7
b101 :
1'
1+
#60
0'
0+
#61
b111 7
b110 :
1'
1+
#62
0'
0+
#63
b0 7
b111 :
1'
1+
#64
0'
0+
#65
b1 7
b0 :
1'
1+
#66
0'
0+
#67
b10 7
b1 :
1'
1+
#68
0'
0+
#69
b11 7
b10 :
1'
1+
#70
0'
0+
#71
b100 7
b11 :
1'
1+
#72
0'
0+
#73
b101 7
b100 :
1'
1+
#74
0'
0+
#75
b110 7
b101 :
1'
1+
#76
0'
0+
#77
b111 7
b110 :
1'
1+
#78
0'
0+
#79
b0 7
b111 :
1'
1+
#80
0'
0+
#81
b1 7
b0 :
1'
1+
#82
0'
0+
#83
b10 7
b1 :
1'
1+
#84
0'
0+
#85
b11 7
b10 :
1'
1+
#86
0'
0+
#87
b100 7
b11 :
1'
1+
#88
0'
0+
#89
b101 7
b100 :
1'
1+
#90
0'
0+
#91
b110 7
b101 :
1'
1+
#92
0'
0+
#93
b111 7
b110 :
1'
1+
#94
0'
0+
#95
b0 7
b111 :
1'
1+
#96
0'
0+
#97
b1 7
b0 :
1'
1+
#98
0'
0+
#99
b10 7
b1 :
1'
1+
#100
0'
0+
#101
b11 7
b10 :
1'
1+
#102
0'
0+
#103
b100 7
b11 :
1'
1+
#104
0'
0+
#105
b101 7
b100 :
1'
1+
#106
0'
0+
#107
b110 7
b101 :
1'
1+
#108
0'
0+
#109
b111 7
b110 :
1'
1+
#110
0'
0+
#111
b0 7
b111 :
1'
1+
#112
0'
0+
#113
b1 7
b0 :
1'
1+
#114
0'
0+
#115
b10 7
b1 :
1'
1+
#116
0'
0+
#117
b11 7
b10 :
1'
1+
#118
0'
0+
#119
b100 7
b11 :
1'
1+
#120
0'
0+
#121
b101 7
b100 :
1'
1+
#122
0'
0+
#123
b110 7
b101 :
1'
1+
#124
0'
0+
#125
b111 7
b110 :
1'
1+
#126
0'
0+
#127
b0 7
b111 :
1'
1+
#128
0'
0+
#129
b1 7
b0 :
1'
1+
#130
0'
0+
#131
b10 7
b1 :
1'
1+
#132
0'
0+
#133
b11 7
b10 :
1'
1+
#134
0'
0+
#135
b100 7
b11 :
1'
1+
#136
0'
0+
#137
b101 7
b100 :
1'
1+
#138
0'
0+
#139
b110 7
b101 :
1'
1+
#140
0'
0+
#141
b111 7
b110 :
1'
1+
#142
0'
0+
#143
b0 7
b111 :
1'
1+
#144
0'
0+
#145
b1 7
b0 :
1'
1+
#146
0'
0+
#147
b10 7
b1 :
1'
1+
#148
b0 7
0'
0+
b1010110 )
b1010110 -
b1010110 2
b1010110 5
#149
b0 :
1'
1+
#150
0.
0'
0+
b0 )
b0 -
b0 2
b0 5
0(
0,
#151
1'
1+
#152
1.
0'
0+
1(
1,
